privacy_meter/__init__.py
privacy_meter/audit.py
privacy_meter/audit_report.py
privacy_meter/constants.py
privacy_meter/dataset.py
privacy_meter/hypothesis_test.py
privacy_meter/information_source.py
privacy_meter/information_source_signal.py
privacy_meter/metric.py
privacy_meter/metric_result.py
privacy_meter/model.py
privacy_meter/utils.py
Privacy_Meter-1.0.1.dist-info/LICENSE
Privacy_Meter-1.0.1.dist-info/METADATA
Privacy_Meter-1.0.1.dist-info/WHEEL
Privacy_Meter-1.0.1.dist-info/top_level.txt
Privacy_Meter-1.0.1.dist-info/RECORD
