Metadata-Version: 2.1
Name: Privacy-Meter
Version: 1.0.1
Summary: Privacy Meter: An open-source library to audit data privacy in statistical and machine learning algorithms.
Home-page: https://github.com/privacytrustlab/ml_privacy_meter
Author-email: reza@comp.nus.edu.sg
Maintainer: Hongyan Chang
Maintainer-email: hongyan@comp.nus.edu.sg
License: MIT
Classifier: License :: OSI Approved :: MIT License
Classifier: Programming Language :: Python :: 3
Requires-Python: >=3.8.0
License-File: LICENSE
